{
  "schemaVersion": 1,
  "id": "taiyitist-translate",
  "name": "Taiyitist Translate",
  "version": "${version}",
  "environment": "server",
  "license": "LGPL-v3.0",
  "authors": [
    "TaiyitistMC Dev Team"
  ],
  "contact": {
    "homepage": "https://github.com/TaiyitistMC/taiyitist",
    "sources": "https://github.com/TaiyitistMC/taiyitist"
  },
  "mixins": [
    "taiyitist.translate.mixins.json"
  ],
  "depends": {
    "fabricloader": ">=${loader_version}",
    "java": ">=${java_version}"
  },
  "description": "The Translator of Taiyitist Server."
}